{
  "AltLookAngle": {
    "x": 0,
    "y": 0,
    "z": 0
  },
  "Autoraise": true,
  "CardID": 232820,
  "ColorDiffuse": {
    "b": 0.71324,
    "g": 0.71324,
    "r": 0.71324
  },
  "CustomDeck": {
    "2328": {
      "BackIsHidden": true,
      "BackURL": "https://dl.dropboxusercontent.com/scl/fi/8wwkdtp83s8b1qs7a992u/c9834325673b4ac5b756434b9e94bce6.jpg?rlkey=ej7b5c7am0a6arusrt6zd62n7&dl=0",
      "FaceURL": "https://dl.dropboxusercontent.com/scl/fi/vc3hed6igm320t1g5fw6c/02b76c52ad5e4cebb54dcece01edfaa6.jpg?rlkey=ndlyt9iw6f5i7p0b8od6duoly&dl=0",
      "NumHeight": 7,
      "NumWidth": 10,
      "Type": 0,
      "UniqueBack": false
    }
  },
  "Description": "Знамение.",
  "DragSelectable": true,
  "GMNotes_path": "TheDunwichLegacy.2898f6/1bTheHouseAlwaysWins.e3aa5c/EncounterDeck.50fc37/TwistofFate.9d6b4c.gmnotes",
  "GUID": "9d6b4c",
  "Grid": true,
  "GridProjection": false,
  "Hands": true,
  "HideWhenFaceDown": true,
  "IgnoreFoW": false,
  "LayoutGroupSortIndex": 0,
  "Locked": false,
  "LuaScript": "",
  "LuaScriptState": "",
  "MeasureMovement": false,
  "Name": "Card",
  "Nickname": "Ирония судьбы",
  "SidewaysCard": false,
  "Snap": true,
  "Sticky": true,
  "Tags": [
    "ScenarioCard"
  ],
  "Tooltip": true,
  "Transform": {
    "posX": 2.707,
    "posY": 1.709,
    "posZ": 9.092,
    "rotX": 0,
    "rotY": 270,
    "rotZ": 0,
    "scaleX": 1,
    "scaleY": 1,
    "scaleZ": 1
  },
  "Value": 0,
  "XmlUI": ""
}